{
  "TEATOP第一味": {
    "高山青": 35.0,
    "當代雙Q": 60.0,
    "百香鮮QQ": 65.0,
    "奶蓋喬麥茶": 65.0
  },
  "清心福全": {
    "烏龍綠": 35.0,
    "優多綠": 50.0,
    "冬瓜青茶": 40.0
  },
  "得正": {
    "輕烏龍": 35.0,
    "輕烏龍鮮奶": 60.0,
    "焙烏龍奶茶": 45.0
  },
  "迷客夏": {
    "大正紅茶拿鐵": 60.0,
    "手炒黑糖鮮奶": 85.0,
    "珍珠鮮奶": 90.0
  },
  "麻古茶坊": {
    "楊枝甘露2.0": 85.0,
    "芝芝芒果果粒": 90.0,
    "香橙果粒茶": 75.0
  },
  "茶湯會": {
    "觀音拿鐵": 65.0,
    "翡翠檸檬": 60.0,
    "新鮮水果茶": 65.0
  },
  "一沐日": {
    "奶蓋喬麥茶": 65.0,
    "粉粿黑糖奶茶": 65.0,
    "荔枝蘆薈": 60.0,
  },
  "五桐號": {
    "觀音拿鐵": 65.0,
    "翡翠檸檬": 60.0,
    "新鮮水果茶": 65.0
}
